iterassert/__init__.py
iterassert/py.typed
pytest_iterassert-0.0.3.dist-info/LICENSE
pytest_iterassert-0.0.3.dist-info/WHEEL
pytest_iterassert-0.0.3.dist-info/METADATA
pytest_iterassert-0.0.3.dist-info/RECORD
