Metadata-Version: 2.1
Name: pytest-iterassert
Version: 0.0.3
Summary: Nicer list and iterable assertion messages for pytest
Home-page: https://github.com/tobywf/pytest-iterassert
License: MPL-2.0
Author: Toby Fleming
Author-email: tobywf@users.noreply.github.com
Requires-Python: >=3.6,<4.0
Classifier: Development Status :: 3 - Alpha
Classifier: Framework :: Pytest
Classifier: Intended Audience :: Developers
Classifier: License :: OSI Approved
Classifier: Natural Language :: English
Classifier: Operating System :: OS Independent
Classifier: Programming Language :: Python :: 3
Classifier: Programming Language :: Python :: 3 :: Only
Classifier: Programming Language :: Python :: 3.6
Classifier: Programming Language :: Python :: 3.7
Classifier: Programming Language :: Python :: 3.8
Classifier: Topic :: Software Development :: Testing
Classifier: Topic :: Software Development :: Testing :: Unit
